minimind/Conv2D.py
minimind/TinyMLP.py
minimind/__init__.py
minimind/base.py
minimind/dl.py
minimind/gan.py
minimind/gpm.py
minimind/layers.py
minimind/ml.py
minimind/nn.py
minimind/sampling.py
minimind/sap.py
minimind/seprod.py
minimind/tokenizer.py
minimind/utils.py
minimind/vae.py
minimind/datasets/MLdata.csv
minimind/datasets/__init__.py
minimind-0.3.312.dist-info/METADATA
minimind-0.3.312.dist-info/WHEEL
minimind-0.3.312.dist-info/top_level.txt
minimind-0.3.312.dist-info/RECORD
