Metadata-Version: 2.4
Name: minimind
Version: 0.3.312
Summary: MiniMind: Lightweight and flexible AI generation library
Home-page: https://github.com/INSECT5386/MiniMind
Author: 신유찬
Author-email: shinnara.yuchan@gmail.com
Classifier: Programming Language :: Python :: 3
Classifier: Operating System :: OS Independent
Classifier: License :: OSI Approved :: MIT License
Classifier: Topic :: Scientific/Engineering :: Artificial Intelligence
Requires-Python: >=3.8
Requires-Dist: numpy>=1.21
Requires-Dist: scikit-learn>=1.0
Requires-Dist: autograd>=1.3
Requires-Dist: joblib>=1.2
Dynamic: author
Dynamic: author-email
Dynamic: classifier
Dynamic: description
Dynamic: description-content-type
Dynamic: home-page
Dynamic: requires-dist
Dynamic: requires-python
Dynamic: summary
